{"v":"5.10.2","fr":60,"ip":0,"op":95,"w":500,"h":500,"nm":"02 coin","ddd":0,"assets":[{"id":"comp_0","nm":"Coin","fr":60,"layers":[{"ddd":0,"ind":1,"ty":4,"nm":"Lines","sr":1,"ks":{"o":{"a":0,"k":100,"ix":11},"r":{"a":0,"k":0,"ix":10},"p":{"a":0,"k":[249.5,250,0],"ix":2,"l":2},"a":{"a":0,"k":[0,0,0],"ix":1,"l":2},"s":{"a":0,"k":[100,100,100],"ix":6,"l":2}},"ao":0,"shapes":[{"ty":"gr","it":[{"ind":0,"ty":"sh","ix":1,"ks":{"a":1,"k":[{"i":{"x":0.833,"y":0.833},"o":{"x":0.167,"y":0.167},"t":0,"s":[{"i":[[0,0],[0,0]],"o":[[0,0],[0,0]],"v":[[172,2],[172,0]],"c":false}]},{"i":{"x":0.833,"y":0.833},"o":{"x":0.167,"y":0.167},"t":13,"s":[{"i":[[0,0],[0,0]],"o":[[0,0],[0,0]],"v":[[172,2],[172,43.724]],"c":false}]},{"i":{"x":0.833,"y":0.833},"o":{"x":0.167,"y":0.167},"t":19,"s":[{"i":[[0,0],[0,0]],"o":[[0,0],[0,0]],"v":[[172,2],[172,65]],"c":false}]},{"i":{"x":0.833,"y":0.833},"o":{"x":0.167,"y":0.167},"t":21,"s":[{"i":[[0,0],[0,0]],"o":[[0,0],[0,0]],"v":[[172,2],[172,60]],"c":false}]},{"i":{"x":0.833,"y":0.833},"o":{"x":0.167,"y":0.167},"t":27,"s":[{"i":[[0,0],[0,0]],"o":[[0,0],[0,0]],"v":[[172,2],[172,42.5]],"c":false}]},{"i":{"x":0.833,"y":0.833},"o":{"x":0.167,"y":0.167},"t":29,"s":[{"i":[[0,0],[0,0]],"o":[[0,0],[0,0]],"v":[[172,2],[172,30]],"c":false}]},{"i":{"x":0.833,"y":0.833},"o":{"x":0.167,"y":0.167},"t":39,"s":[{"i":[[0,0],[0,0]],"o":[[0,0],[0,0]],"v":[[172,2],[172,16.5]],"c":false}]},{"i":{"x":0.833,"y":0.833},"o":{"x":0.167,"y":0.167},"t":43,"s":[{"i":[[0,0],[0,0]],"o":[[0,0],[0,0]],"v":[[172,2],[172,18]],"c":false}]},{"i":{"x":0.833,"y":0.833},"o":{"x":0.167,"y":0.167},"t":47,"s":[{"i":[[0,0],[0,0]],"o":[[0,0],[0,0]],"v":[[172,2],[172,30.179]],"c":false}]},{"i":{"x":0.833,"y":0.833},"o":{"x":0.167,"y":0.167},"t":51,"s":[{"i":[[0,0],[0,0]],"o":[[0,0],[0,0]],"v":[[172,-4],[172,42.959]],"c":false}]},{"i":{"x":0.833,"y":0.833},"o":{"x":0.167,"y":0.167},"t":52,"s":[{"i":[[0,0],[0,0]],"o":[[0,0],[0,0]],"v":[[172,0],[172,46.154]],"c":false}]},{"i":{"x":0.833,"y":0.833},"o":{"x":0.167,"y":0.167},"t":56,"s":[{"i":[[0,0],[0,0]],"o":[[0,0],[0,0]],"v":[[172,2],[172,62]],"c":false}]},{"i":{"x":0.833,"y":0.833},"o":{"x":0.167,"y":0.167},"t":61,"s":[{"i":[[0,0],[0,0]],"o":[[0,0],[0,0]],"v":[[172,2],[172,44]],"c":false}]},{"i":{"x":0.833,"y":0.833},"o":{"x":0.167,"y":0.167},"t":64,"s":[{"i":[[0,0],[0,0]],"o":[[0,0],[0,0]],"v":[[172,2],[172,32]],"c":false}]},{"i":{"x":0.833,"y":0.833},"o":{"x":0.167,"y":0.167},"t":67,"s":[{"i":[[0,0],[0,0]],"o":[[0,0],[0,0]],"v":[[172,2],[172,16.5]],"c":false}]},{"t":69,"s":[{"i":[[0,0],[0,0]],"o":[[0,0],[0,0]],"v":[[172,2],[172,0]],"c":false}]}],"ix":2},"nm":"Path 1","mn":"ADBE Vector Shape - Group","hd":false},{"ty":"st","c":{"a":0,"k":[0,0,0,1],"ix":3,"x":"var $bm_rt;\n$bm_rt = comp('02 coin').layer('Main Stroke width - Color Ctrl').effect('Base Color')('Color');"},"o":{"a":0,"k":100,"ix":4},"w":{"a":0,"k":16,"ix":5,"x":"var $bm_rt;\n$bm_rt = comp('02 coin').layer('Main Stroke width - Color Ctrl').effect('Stroke width')('Slider');"},"lc":2,"lj":1,"ml":4,"bm":0,"nm":"Stroke 1","mn":"ADBE Vector Graphic - Stroke","hd":false},{"ty":"tr","p":{"a":0,"k":[0,0],"ix":2},"a":{"a":0,"k":[0,0],"ix":1},"s":{"a":0,"k":[100,100],"ix":3},"r":{"a":0,"k":0,"ix":6},"o":{"a":0,"k":100,"ix":7},"sk":{"a":0,"k":0,"ix":4},"sa":{"a":0,"k":0,"ix":5},"nm":"Transform"}],"nm":"Shape 2","np":3,"cix":2,"bm":0,"ix":1,"mn":"ADBE Vector Group","hd":false},{"ty":"gr","it":[{"ind":0,"ty":"sh","ix":1,"ks":{"a":1,"k":[{"i":{"x":0.833,"y":0.833},"o":{"x":0.167,"y":0.167},"t":0,"s":[{"i":[[0,0],[0,0]],"o":[[0,0],[0,0]],"v":[[-172,1],[-172,1]],"c":false}]},{"i":{"x":0.833,"y":0.833},"o":{"x":0.167,"y":0.167},"t":13,"s":[{"i":[[0,0],[0,0]],"o":[[0,0],[0,0]],"v":[[-172,1],[-172,44.724]],"c":false}]},{"i":{"x":0.833,"y":0.833},"o":{"x":0.167,"y":0.167},"t":19,"s":[{"i":[[0,0],[0,0]],"o":[[0,0],[0,0]],"v":[[-172,1],[-172,66]],"c":false}]},{"i":{"x":0.833,"y":0.833},"o":{"x":0.167,"y":0.167},"t":21,"s":[{"i":[[0,0],[0,0]],"o":[[0,0],[0,0]],"v":[[-172,1],[-172,61]],"c":false}]},{"i":{"x":0.833,"y":0.833},"o":{"x":0.167,"y":0.167},"t":27,"s":[{"i":[[0,0],[0,0]],"o":[[0,0],[0,0]],"v":[[-172,1],[-172,43.5]],"c":false}]},{"i":{"x":0.833,"y":0.833},"o":{"x":0.167,"y":0.167},"t":29,"s":[{"i":[[0,0],[0,0]],"o":[[0,0],[0,0]],"v":[[-172,1],[-172,31]],"c":false}]},{"i":{"x":0.833,"y":0.833},"o":{"x":0.167,"y":0.167},"t":39,"s":[{"i":[[0,0],[0,0]],"o":[[0,0],[0,0]],"v":[[-172,1],[-172,17.5]],"c":false}]},{"i":{"x":0.833,"y":0.833},"o":{"x":0.167,"y":0.167},"t":43,"s":[{"i":[[0,0],[0,0]],"o":[[0,0],[0,0]],"v":[[-172,1],[-172,19]],"c":false}]},{"i":{"x":0.833,"y":0.833},"o":{"x":0.167,"y":0.167},"t":47,"s":[{"i":[[0,0],[0,0]],"o":[[0,0],[0,0]],"v":[[-172,1],[-172,31.179]],"c":false}]},{"i":{"x":0.833,"y":0.833},"o":{"x":0.167,"y":0.167},"t":51,"s":[{"i":[[0,0],[0,0]],"o":[[0,0],[0,0]],"v":[[-172,-5],[-172,43.959]],"c":false}]},{"i":{"x":0.833,"y":0.833},"o":{"x":0.167,"y":0.167},"t":52,"s":[{"i":[[0,0],[0,0]],"o":[[0,0],[0,0]],"v":[[-172,-1],[-172,47.154]],"c":false}]},{"i":{"x":0.833,"y":0.833},"o":{"x":0.167,"y":0.167},"t":56,"s":[{"i":[[0,0],[0,0]],"o":[[0,0],[0,0]],"v":[[-172,1],[-172,63]],"c":false}]},{"i":{"x":0.833,"y":0.833},"o":{"x":0.167,"y":0.167},"t":61,"s":[{"i":[[0,0],[0,0]],"o":[[0,0],[0,0]],"v":[[-172,1],[-172,45]],"c":false}]},{"i":{"x":0.833,"y":0.833},"o":{"x":0.167,"y":0.167},"t":64,"s":[{"i":[[0,0],[0,0]],"o":[[0,0],[0,0]],"v":[[-172,1],[-172,33]],"c":false}]},{"i":{"x":0.833,"y":0.833},"o":{"x":0.167,"y":0.167},"t":67,"s":[{"i":[[0,0],[0,0]],"o":[[0,0],[0,0]],"v":[[-172,1],[-172,17.5]],"c":false}]},{"t":69,"s":[{"i":[[0,0],[0,0]],"o":[[0,0],[0,0]],"v":[[-172,1],[-172,1]],"c":false}]}],"ix":2},"nm":"Path 1","mn":"ADBE Vector Shape - Group","hd":false},{"ty":"st","c":{"a":0,"k":[0,0,0,1],"ix":3,"x":"var $bm_rt;\n$bm_rt = comp('02 coin').layer('Main Stroke width - Color Ctrl').effect('Base Color')('Color');"},"o":{"a":0,"k":100,"ix":4},"w":{"a":0,"k":16,"ix":5,"x":"var $bm_rt;\n$bm_rt = comp('02 coin').layer('Main Stroke width - Color Ctrl').effect('Stroke width')('Slider');"},"lc":2,"lj":1,"ml":4,"bm":0,"nm":"Stroke 1","mn":"ADBE Vector Graphic - Stroke","hd":false},{"ty":"tr","p":{"a":0,"k":[1,0],"ix":2},"a":{"a":0,"k":[0,0],"ix":1},"s":{"a":0,"k":[100,100],"ix":3},"r":{"a":0,"k":0,"ix":6},"o":{"a":0,"k":100,"ix":7},"sk":{"a":0,"k":0,"ix":4},"sa":{"a":0,"k":0,"ix":5},"nm":"Transform"}],"nm":"Shape 1","np":3,"cix":2,"bm":0,"ix":2,"mn":"ADBE Vector Group","hd":false}],"ip":0,"op":120,"st":0,"ct":1,"bm":0},{"ddd":0,"ind":3,"ty":4,"nm":"coin 10","parent":4,"sr":1,"ks":{"o":{"a":0,"k":100,"ix":11},"r":{"a":0,"k":0,"ix":10},"p":{"a":1,"k":[{"i":{"x":0.833,"y":0.833},"o":{"x":0.167,"y":0.167},"t":39,"s":[0,0,0],"to":[0,-6.5,0],"ti":[0,6.5,0]},{"t":50,"s":[0,-39,0]}],"ix":2,"l":2},"a":{"a":0,"k":[0,0,0],"ix":1,"l":2},"s":{"a":0,"k":[100,100,100],"ix":6,"l":2}},"ao":0,"shapes":[{"ty":"gr","it":[{"ind":0,"ty":"sh","ix":1,"ks":{"a":1,"k":[{"i":{"x":0.79,"y":1},"o":{"x":0.21,"y":0},"t":0,"s":[{"i":[[0,0],[0,0]],"o":[[0,0],[0,0]],"v":[[-45.733,-45.333],[45.733,-45.333]],"c":true}]},{"i":{"x":0.79,"y":1},"o":{"x":0.21,"y":0},"t":39,"s":[{"i":[[0,0],[0,0]],"o":[[0,0],[0,0]],"v":[[-45.733,45.733],[45.733,45.733]],"c":true}]},{"t":73,"s":[{"i":[[0,0],[0,0]],"o":[[0,0],[0,0]],"v":[[-45.733,-45.333],[45.733,-45.333]],"c":true}]}],"ix":2},"nm":"Path 1","mn":"ADBE Vector Shape - Group","hd":false},{"ty":"st","c":{"a":0,"k":[0,0,0,1],"ix":3,"x":"var $bm_rt;\n$bm_rt = comp('02 coin').layer('Main Stroke width - Color Ctrl').effect('Base Color')('Color');"},"o":{"a":0,"k":100,"ix":4},"w":{"a":0,"k":16,"ix":5,"x":"var $bm_rt;\n$bm_rt = comp('02 coin').layer('Main Stroke width - Color Ctrl').effect('Stroke width')('Slider');"},"lc":2,"lj":2,"bm":0,"nm":"Stroke 1","mn":"ADBE Vector Graphic - Stroke","hd":false},{"ty":"tr","p":{"a":0,"k":[0,0],"ix":2},"a":{"a":0,"k":[0,0],"ix":1},"s":{"a":0,"k":[100,100],"ix":3},"r":{"a":0,"k":0,"ix":6},"o":{"a":0,"k":100,"ix":7},"sk":{"a":0,"k":0,"ix":4},"sa":{"a":0,"k":0,"ix":5},"nm":"Transform"}],"nm":"Group 1","np":2,"cix":2,"bm":0,"ix":1,"mn":"ADBE Vector Group","hd":false}],"ip":39,"op":50,"st":0,"ct":1,"bm":0},{"ddd":0,"ind":4,"ty":4,"nm":"coin 5","sr":1,"ks":{"o":{"a":0,"k":100,"ix":11},"r":{"a":0,"k":0,"ix":10},"p":{"a":1,"k":[{"i":{"x":0.833,"y":0.833},"o":{"x":0.167,"y":0.167},"t":0,"s":[250,250,0],"to":[0,11,0],"ti":[0,0,0]},{"i":{"x":0.833,"y":0.833},"o":{"x":0.167,"y":0.167},"t":19,"s":[250,316,0],"to":[0,0,0],"ti":[0,0,0]},{"i":{"x":0.833,"y":0.833},"o":{"x":0.167,"y":0.167},"t":39,"s":[250,250,0],"to":[0,0,0],"ti":[0,0,0]},{"i":{"x":0.833,"y":0.833},"o":{"x":0.167,"y":0.167},"t":56,"s":[250,316,0],"to":[0,0,0],"ti":[0,11,0]},{"t":73,"s":[250,250,0]}],"ix":2,"l":2},"a":{"a":0,"k":[0,0,0],"ix":1,"l":2},"s":{"a":0,"k":[100,100,100],"ix":6,"l":2}},"ao":0,"shapes":[{"ty":"gr","it":[{"ind":0,"ty":"sh","ix":1,"ks":{"a":1,"k":[{"i":{"x":0.79,"y":1},"o":{"x":0.21,"y":0},"t":0,"s":[{"i":[[0,0],[0,0],[0,0],[0,0]],"o":[[0,0],[0,0],[0,0],[0,0]],"v":[[-45.733,-45.333],[45.733,-45.333],[45.733,45.333],[-45.733,45.333]],"c":true}]},{"i":{"x":0.79,"y":1},"o":{"x":0.21,"y":0},"t":39,"s":[{"i":[[0,0],[0,0],[0,0],[0,0]],"o":[[0,0],[0,0],[0,0],[0,0]],"v":[[-45.733,45.733],[45.733,45.733],[45.733,-45.733],[-45.733,-45.733]],"c":true}]},{"t":73,"s":[{"i":[[0,0],[0,0],[0,0],[0,0]],"o":[[0,0],[0,0],[0,0],[0,0]],"v":[[-45.733,-45.333],[45.733,-45.333],[45.733,45.333],[-45.733,45.333]],"c":true}]}],"ix":2},"nm":"Path 1","mn":"ADBE Vector Shape - Group","hd":false},{"ty":"st","c":{"a":0,"k":[0,0,0,1],"ix":3,"x":"var $bm_rt;\n$bm_rt = comp('02 coin').layer('Main Stroke width - Color Ctrl').effect('Base Color')('Color');"},"o":{"a":0,"k":100,"ix":4},"w":{"a":0,"k":16,"ix":5,"x":"var $bm_rt;\n$bm_rt = comp('02 coin').layer('Main Stroke width - Color Ctrl').effect('Stroke width')('Slider');"},"lc":2,"lj":2,"bm":0,"nm":"Stroke 1","mn":"ADBE Vector Graphic - Stroke","hd":false},{"ty":"fl","c":{"a":0,"k":[1,1,1,1],"ix":4},"o":{"a":0,"k":100,"ix":5},"r":1,"bm":0,"nm":"Fill 1","mn":"ADBE Vector Graphic - Fill","hd":false},{"ty":"tr","p":{"a":0,"k":[0,0],"ix":2},"a":{"a":0,"k":[0,0],"ix":1},"s":{"a":0,"k":[100,100],"ix":3},"r":{"a":0,"k":0,"ix":6},"o":{"a":0,"k":100,"ix":7},"sk":{"a":0,"k":0,"ix":4},"sa":{"a":0,"k":0,"ix":5},"nm":"Transform"}],"nm":"Group 1","np":3,"cix":2,"bm":0,"ix":1,"mn":"ADBE Vector Group","hd":false},{"ty":"gr","it":[{"ind":0,"ty":"sh","ix":1,"ks":{"a":1,"k":[{"i":{"x":0.79,"y":1},"o":{"x":0.21,"y":0},"t":0,"s":[{"i":[[-69.413,0],[0,68.805],[69.412,0],[0,-68.805]],"o":[[69.413,0],[0,-68.805],[-69.412,0],[0,68.805]],"v":[[0,124.667],[125.767,0],[0,-124.667],[-125.767,0]],"c":true}]},{"i":{"x":0.79,"y":1},"o":{"x":0.21,"y":0},"t":39,"s":[{"i":[[-69.412,0],[0,-69.412],[69.413,0],[0,69.412]],"o":[[69.413,0],[0,69.412],[-69.412,0],[0,-69.412]],"v":[[0,-125.767],[125.767,0],[0,125.767],[-125.767,0]],"c":true}]},{"t":73,"s":[{"i":[[-69.413,0],[0,68.805],[69.412,0],[0,-68.805]],"o":[[69.413,0],[0,-68.805],[-69.412,0],[0,68.805]],"v":[[0,124.667],[125.767,0],[0,-124.667],[-125.767,0]],"c":true}]}],"ix":2},"nm":"Path 1","mn":"ADBE Vector Shape - Group","hd":false},{"ty":"st","c":{"a":0,"k":[0.20000000298,0.800000011921,0.800000011921,1],"ix":3,"x":"var $bm_rt;\n$bm_rt = comp('02 coin').layer('Main Stroke width - Color Ctrl').effect('Base Color')('Color');"},"o":{"a":0,"k":100,"ix":4},"w":{"a":0,"k":16,"ix":5,"x":"var $bm_rt;\n$bm_rt = comp('02 coin').layer('Main Stroke width - Color Ctrl').effect('Stroke width')('Slider');"},"lc":2,"lj":2,"bm":0,"nm":"Stroke 1","mn":"ADBE Vector Graphic - Stroke","hd":false},{"ty":"fl","c":{"a":0,"k":[0.992156862745,0.796078431373,0.313725490196,1],"ix":4},"o":{"a":0,"k":100,"ix":5},"r":1,"bm":0,"nm":"Fill 1","mn":"ADBE Vector Graphic - Fill","hd":false},{"ty":"tr","p":{"a":0,"k":[0,0],"ix":2},"a":{"a":0,"k":[0,0],"ix":1},"s":{"a":0,"k":[100,100],"ix":3},"r":{"a":0,"k":0,"ix":6},"o":{"a":0,"k":100,"ix":7},"sk":{"a":0,"k":0,"ix":4},"sa":{"a":0,"k":0,"ix":5},"nm":"Transform"}],"nm":"Group 2","np":3,"cix":2,"bm":0,"ix":2,"mn":"ADBE Vector Group","hd":false},{"ty":"gr","it":[{"ind":0,"ty":"sh","ix":1,"ks":{"a":1,"k":[{"i":{"x":0.79,"y":1},"o":{"x":0.21,"y":0},"t":0,"s":[{"i":[[-94.654,0],[0,93.823],[94.653,0],[0,-93.823]],"o":[[94.654,0],[0,-93.823],[-94.653,0],[0,93.823]],"v":[[0,170],[171.5,0],[0,-170],[-171.5,0]],"c":true}]},{"i":{"x":0.79,"y":1},"o":{"x":0.21,"y":0},"t":39,"s":[{"i":[[-94.653,0],[0,-94.651],[94.654,0],[0,94.651]],"o":[[94.654,0],[0,94.651],[-94.653,0],[0,-94.651]],"v":[[0,-171.5],[171.5,0],[0,171.5],[-171.5,0]],"c":true}]},{"t":73,"s":[{"i":[[-94.654,0],[0,93.823],[94.653,0],[0,-93.823]],"o":[[94.654,0],[0,-93.823],[-94.653,0],[0,93.823]],"v":[[0,170],[171.5,0],[0,-170],[-171.5,0]],"c":true}]}],"ix":2},"nm":"Path 1","mn":"ADBE Vector Shape - Group","hd":false},{"ty":"st","c":{"a":0,"k":[0,0,0,1],"ix":3,"x":"var $bm_rt;\n$bm_rt = comp('02 coin').layer('Main Stroke width - Color Ctrl').effect('Base Color')('Color');"},"o":{"a":0,"k":100,"ix":4},"w":{"a":0,"k":16,"ix":5,"x":"var $bm_rt;\n$bm_rt = comp('02 coin').layer('Main Stroke width - Color Ctrl').effect('Stroke width')('Slider');"},"lc":2,"lj":2,"bm":0,"nm":"Stroke 1","mn":"ADBE Vector Graphic - Stroke","hd":false},{"ty":"fl","c":{"a":0,"k":[0.992156862745,0.560784313725,0.003921568627,1],"ix":4},"o":{"a":0,"k":100,"ix":5},"r":1,"bm":0,"nm":"Fill 1","mn":"ADBE Vector Graphic - Fill","hd":false},{"ty":"tr","p":{"a":0,"k":[0,0],"ix":2},"a":{"a":0,"k":[0,0],"ix":1},"s":{"a":0,"k":[100,100],"ix":3},"r":{"a":0,"k":0,"ix":6},"o":{"a":0,"k":100,"ix":7},"sk":{"a":0,"k":0,"ix":4},"sa":{"a":0,"k":0,"ix":5},"nm":"Transform"}],"nm":"Group 3","np":3,"cix":2,"bm":0,"ix":3,"mn":"ADBE Vector Group","hd":false}],"ip":39,"op":120,"st":0,"ct":1,"bm":0},{"ddd":0,"ind":5,"ty":4,"nm":"coin 7","td":1,"sr":1,"ks":{"o":{"a":0,"k":100,"ix":11},"r":{"a":0,"k":0,"ix":10},"p":{"a":1,"k":[{"i":{"x":0.833,"y":0.833},"o":{"x":0.167,"y":0.167},"t":0,"s":[250,250,0],"to":[0,11,0],"ti":[0,0,0]},{"i":{"x":0.833,"y":0.833},"o":{"x":0.167,"y":0.167},"t":19,"s":[250,316,0],"to":[0,0,0],"ti":[0,0,0]},{"i":{"x":0.833,"y":0.833},"o":{"x":0.167,"y":0.167},"t":39,"s":[250,250,0],"to":[0,0,0],"ti":[0,0,0]},{"i":{"x":0.833,"y":0.833},"o":{"x":0.167,"y":0.167},"t":42,"s":[250,264.013,0],"to":[0,0,0],"ti":[0,0,0]},{"i":{"x":0.833,"y":0.833},"o":{"x":0.167,"y":0.167},"t":44,"s":[250,272.941,0],"to":[0,0,0],"ti":[0,0,0]},{"i":{"x":0.833,"y":0.833},"o":{"x":0.167,"y":0.167},"t":46,"s":[250,286.865,0],"to":[0,0,0],"ti":[0,0,0]},{"i":{"x":0.833,"y":0.833},"o":{"x":0.167,"y":0.167},"t":48,"s":[250,288.29,0],"to":[0,0,0],"ti":[0,0,0]},{"i":{"x":0.833,"y":0.833},"o":{"x":0.167,"y":0.167},"t":50,"s":[250,284.704,0],"to":[0,0,0],"ti":[0,0,0]},{"i":{"x":0.833,"y":0.833},"o":{"x":0.167,"y":0.167},"t":52,"s":[250,277.137,0],"to":[0,0,0],"ti":[0,0,0]},{"i":{"x":0.833,"y":0.833},"o":{"x":0.167,"y":0.167},"t":53,"s":[250,270.857,0],"to":[0,0,0],"ti":[0,0,0]},{"i":{"x":0.833,"y":0.833},"o":{"x":0.167,"y":0.167},"t":54,"s":[250,267.24,0],"to":[0,0,0],"ti":[0,0,0]},{"i":{"x":0.833,"y":0.833},"o":{"x":0.167,"y":0.167},"t":55,"s":[250,264.62,0],"to":[0,0,0],"ti":[0,0,0]},{"i":{"x":0.833,"y":0.833},"o":{"x":0.167,"y":0.167},"t":56,"s":[250,269,0],"to":[0,0,0],"ti":[0,2.449,0]},{"i":{"x":0.833,"y":0.833},"o":{"x":0.167,"y":0.167},"t":57,"s":[250,265.118,0],"to":[0,-0.329,0],"ti":[0,0.304,0]},{"i":{"x":0.833,"y":0.833},"o":{"x":0.167,"y":0.167},"t":58,"s":[250,266.168,0],"to":[0,-0.379,0],"ti":[0,0.345,0]},{"i":{"x":0.833,"y":0.833},"o":{"x":0.167,"y":0.167},"t":59,"s":[250,271.083,0],"to":[0,-0.392,0],"ti":[0,0.144,0]},{"i":{"x":0.833,"y":0.833},"o":{"x":0.167,"y":0.167},"t":60,"s":[250,275.361,0],"to":[0,-0.189,0],"ti":[0,0.414,0]},{"i":{"x":0.833,"y":0.833},"o":{"x":0.167,"y":0.167},"t":61,"s":[250,282.641,0],"to":[0,-0.573,0],"ti":[0,1.279,0]},{"i":{"x":0.833,"y":0.833},"o":{"x":0.167,"y":0.167},"t":62,"s":[250,286.503,0],"to":[0,-1.311,0],"ti":[0,0.523,0]},{"i":{"x":0.833,"y":0.833},"o":{"x":0.167,"y":0.167},"t":63,"s":[250,289.363,0],"to":[0,-0.659,0],"ti":[0,-3.803,0]},{"i":{"x":0.833,"y":0.833},"o":{"x":0.167,"y":0.167},"t":64,"s":[250,294.331,0],"to":[0,3.924,0],"ti":[0,1.068,0]},{"i":{"x":0.833,"y":0.833},"o":{"x":0.167,"y":0.167},"t":65,"s":[250,290.09,0],"to":[0,-6.653,0],"ti":[0,5.071,0]},{"t":73,"s":[250,250,0]}],"ix":2,"l":2},"a":{"a":0,"k":[0,0,0],"ix":1,"l":2},"s":{"a":0,"k":[100,100,100],"ix":6,"l":2}},"ao":0,"shapes":[{"ty":"gr","it":[{"ind":0,"ty":"sh","ix":1,"ks":{"a":1,"k":[{"i":{"x":0.79,"y":1},"o":{"x":0.21,"y":0},"t":0,"s":[{"i":[[-94.654,0],[0,93.823],[94.653,0],[0,-93.823]],"o":[[94.654,0],[0,-93.823],[-94.653,0],[0,93.823]],"v":[[0,170],[171.5,0],[0,-170],[-171.5,0]],"c":true}]},{"i":{"x":0.79,"y":1},"o":{"x":0.21,"y":0},"t":39,"s":[{"i":[[-94.653,0],[0,-94.651],[94.654,0],[0,94.651]],"o":[[94.654,0],[0,94.651],[-94.653,0],[0,-94.651]],"v":[[0,-171.5],[171.5,0],[0,171.5],[-171.5,0]],"c":true}]},{"t":73,"s":[{"i":[[-94.654,0],[0,93.823],[94.653,0],[0,-93.823]],"o":[[94.654,0],[0,-93.823],[-94.653,0],[0,93.823]],"v":[[0,170],[171.5,0],[0,-170],[-171.5,0]],"c":true}]}],"ix":2},"nm":"Path 1","mn":"ADBE Vector Shape - Group","hd":false},{"ty":"st","c":{"a":0,"k":[0,0,0,1],"ix":3},"o":{"a":0,"k":100,"ix":4},"w":{"a":0,"k":16,"ix":5,"x":"var $bm_rt;\n$bm_rt = comp('02 coin').layer('Main Stroke width - Color Ctrl').effect('Stroke width')('Slider');"},"lc":2,"lj":2,"bm":0,"nm":"Stroke 1","mn":"ADBE Vector Graphic - Stroke","hd":false},{"ty":"tr","p":{"a":0,"k":[0,0],"ix":2},"a":{"a":0,"k":[0,0],"ix":1},"s":{"a":0,"k":[100,100],"ix":3},"r":{"a":0,"k":0,"ix":6},"o":{"a":0,"k":100,"ix":7},"sk":{"a":0,"k":0,"ix":4},"sa":{"a":0,"k":0,"ix":5},"nm":"Transform"}],"nm":"Group 3","np":2,"cix":2,"bm":0,"ix":1,"mn":"ADBE Vector Group","hd":false},{"ty":"gr","it":[{"ind":0,"ty":"sh","ix":1,"ks":{"a":1,"k":[{"i":{"x":0.79,"y":1},"o":{"x":0.21,"y":0},"t":0,"s":[{"i":[[0,0],[0,0],[0,0],[0,0]],"o":[[0,0],[0,0],[0,0],[0,0]],"v":[[-45.733,-45.333],[45.733,-45.333],[45.733,45.333],[-45.733,45.333]],"c":true}]},{"i":{"x":0.79,"y":1},"o":{"x":0.21,"y":0},"t":39,"s":[{"i":[[0,0],[0,0],[0,0],[0,0]],"o":[[0,0],[0,0],[0,0],[0,0]],"v":[[-45.733,45.733],[45.733,45.733],[45.733,-45.733],[-45.733,-45.733]],"c":true}]},{"t":73,"s":[{"i":[[0,0],[0,0],[0,0],[0,0]],"o":[[0,0],[0,0],[0,0],[0,0]],"v":[[-45.733,-45.333],[45.733,-45.333],[45.733,45.333],[-45.733,45.333]],"c":true}]}],"ix":2},"nm":"Path 1","mn":"ADBE Vector Shape - Group","hd":false},{"ty":"st","c":{"a":0,"k":[0,0,0,1],"ix":3},"o":{"a":0,"k":100,"ix":4},"w":{"a":0,"k":16,"ix":5,"x":"var $bm_rt;\n$bm_rt = comp('02 coin').layer('Main Stroke width - Color Ctrl').effect('Stroke width')('Slider');"},"lc":2,"lj":2,"bm":0,"nm":"Stroke 1","mn":"ADBE Vector Graphic - Stroke","hd":false},{"ty":"tr","p":{"a":0,"k":[0,0],"ix":2},"a":{"a":0,"k":[0,0],"ix":1},"s":{"a":0,"k":[100,100],"ix":3},"r":{"a":0,"k":0,"ix":6},"o":{"a":0,"k":100,"ix":7},"sk":{"a":0,"k":0,"ix":4},"sa":{"a":0,"k":0,"ix":5},"nm":"Transform"}],"nm":"Group 1","np":2,"cix":2,"bm":0,"ix":2,"mn":"ADBE Vector Group","hd":false},{"ty":"gr","it":[{"ind":0,"ty":"sh","ix":1,"ks":{"a":1,"k":[{"i":{"x":0.79,"y":1},"o":{"x":0.21,"y":0},"t":0,"s":[{"i":[[-69.413,0],[0,68.805],[69.412,0],[0,-68.805]],"o":[[69.413,0],[0,-68.805],[-69.412,0],[0,68.805]],"v":[[0,124.667],[125.767,0],[0,-124.667],[-125.767,0]],"c":true}]},{"i":{"x":0.79,"y":1},"o":{"x":0.21,"y":0},"t":39,"s":[{"i":[[-69.412,0],[0,-69.412],[69.413,0],[0,69.412]],"o":[[69.413,0],[0,69.412],[-69.412,0],[0,-69.412]],"v":[[0,-125.767],[125.767,0],[0,125.767],[-125.767,0]],"c":true}]},{"t":73,"s":[{"i":[[-69.413,0],[0,68.805],[69.412,0],[0,-68.805]],"o":[[69.413,0],[0,-68.805],[-69.412,0],[0,68.805]],"v":[[0,124.667],[125.767,0],[0,-124.667],[-125.767,0]],"c":true}]}],"ix":2},"nm":"Path 1","mn":"ADBE Vector Shape - Group","hd":false},{"ty":"st","c":{"a":0,"k":[0.20000000298,0.800000011921,0.800000011921,1],"ix":3},"o":{"a":0,"k":100,"ix":4},"w":{"a":0,"k":16,"ix":5,"x":"var $bm_rt;\n$bm_rt = comp('02 coin').layer('Main Stroke width - Color Ctrl').effect('Stroke width')('Slider');"},"lc":2,"lj":2,"bm":0,"nm":"Stroke 1","mn":"ADBE Vector Graphic - Stroke","hd":false},{"ty":"tr","p":{"a":0,"k":[0,0],"ix":2},"a":{"a":0,"k":[0,0],"ix":1},"s":{"a":0,"k":[100,100],"ix":3},"r":{"a":0,"k":0,"ix":6},"o":{"a":0,"k":100,"ix":7},"sk":{"a":0,"k":0,"ix":4},"sa":{"a":0,"k":0,"ix":5},"nm":"Transform"}],"nm":"Group 2","np":2,"cix":2,"bm":0,"ix":3,"mn":"ADBE Vector Group","hd":false},{"ty":"fl","c":{"a":0,"k":[1,0,0,1],"ix":4},"o":{"a":0,"k":100,"ix":5},"r":1,"bm":0,"nm":"Fill 1","mn":"ADBE Vector Graphic - Fill","hd":false}],"ip":39,"op":120,"st":0,"ct":1,"bm":0},{"ddd":0,"ind":6,"ty":4,"nm":"coin 4","tt":2,"tp":5,"sr":1,"ks":{"o":{"a":0,"k":100,"ix":11},"r":{"a":0,"k":0,"ix":10},"p":{"a":0,"k":[250,250,0],"ix":2,"l":2},"a":{"a":0,"k":[0,0,0],"ix":1,"l":2},"s":{"a":0,"k":[100,100,100],"ix":6,"l":2}},"ao":0,"shapes":[{"ty":"gr","it":[{"ind":0,"ty":"sh","ix":1,"ks":{"a":1,"k":[{"i":{"x":0.79,"y":1},"o":{"x":0.21,"y":0},"t":0,"s":[{"i":[[-94.654,0],[0,93.823],[94.653,0],[0,-93.823]],"o":[[94.654,0],[0,-93.823],[-94.653,0],[0,93.823]],"v":[[0,170],[171.5,0],[0,-170],[-171.5,0]],"c":true}]},{"i":{"x":0.79,"y":1},"o":{"x":0.21,"y":0},"t":39,"s":[{"i":[[-94.653,0],[0,-94.651],[94.654,0],[0,94.651]],"o":[[94.654,0],[0,94.651],[-94.653,0],[0,-94.651]],"v":[[0,-171.5],[171.5,0],[0,171.5],[-171.5,0]],"c":true}]},{"t":73,"s":[{"i":[[-94.654,0],[0,93.823],[94.653,0],[0,-93.823]],"o":[[94.654,0],[0,-93.823],[-94.653,0],[0,93.823]],"v":[[0,170],[171.5,0],[0,-170],[-171.5,0]],"c":true}]}],"ix":2},"nm":"Path 1","mn":"ADBE Vector Shape - Group","hd":false},{"ty":"st","c":{"a":0,"k":[0,0,0,1],"ix":3,"x":"var $bm_rt;\n$bm_rt = comp('02 coin').layer('Main Stroke width - Color Ctrl').effect('Base Color')('Color');"},"o":{"a":0,"k":100,"ix":4},"w":{"a":0,"k":16,"ix":5,"x":"var $bm_rt;\n$bm_rt = comp('02 coin').layer('Main Stroke width - Color Ctrl').effect('Stroke width')('Slider');"},"lc":2,"lj":2,"bm":0,"nm":"Stroke 1","mn":"ADBE Vector Graphic - Stroke","hd":false},{"ty":"tr","p":{"a":0,"k":[0,0],"ix":2},"a":{"a":0,"k":[0,0],"ix":1},"s":{"a":0,"k":[100,100],"ix":3},"r":{"a":0,"k":0,"ix":6},"o":{"a":0,"k":100,"ix":7},"sk":{"a":0,"k":0,"ix":4},"sa":{"a":0,"k":0,"ix":5},"nm":"Transform"}],"nm":"Group 3","np":2,"cix":2,"bm":0,"ix":1,"mn":"ADBE Vector Group","hd":false},{"ty":"gr","it":[{"ty":"rc","d":1,"s":{"a":0,"k":[482,472],"ix":2},"p":{"a":0,"k":[0,0],"ix":3},"r":{"a":0,"k":0,"ix":4},"nm":"Rectangle Path 1","mn":"ADBE Vector Shape - Rect","hd":false},{"ty":"st","c":{"a":0,"k":[0,0,0,1],"ix":3},"o":{"a":0,"k":0,"ix":4},"w":{"a":0,"k":16,"ix":5},"lc":1,"lj":1,"ml":4,"bm":0,"nm":"Stroke 1","mn":"ADBE Vector Graphic - Stroke","hd":false},{"ty":"tr","p":{"a":0,"k":[-1,-4],"ix":2},"a":{"a":0,"k":[0,0],"ix":1},"s":{"a":0,"k":[100,100],"ix":3},"r":{"a":0,"k":0,"ix":6},"o":{"a":0,"k":100,"ix":7},"sk":{"a":0,"k":0,"ix":4},"sa":{"a":0,"k":0,"ix":5},"nm":"Transform"}],"nm":"Rectangle 1","np":3,"cix":2,"bm":0,"ix":2,"mn":"ADBE Vector Group","hd":false}],"ip":39,"op":120,"st":0,"ct":1,"bm":0},{"ddd":0,"ind":7,"ty":4,"nm":"coin 3","td":1,"sr":1,"ks":{"o":{"a":0,"k":100,"ix":11},"r":{"a":0,"k":0,"ix":10},"p":{"a":1,"k":[{"i":{"x":0.833,"y":0.833},"o":{"x":0.167,"y":0.167},"t":0,"s":[250,250,0],"to":[0,3.399,0],"ti":[0,-6.36,0]},{"i":{"x":0.833,"y":0.833},"o":{"x":0.167,"y":0.167},"t":7,"s":[250,245.579,0],"to":[0,2.245,0],"ti":[0,-2.972,0]},{"i":{"x":0.833,"y":0.833},"o":{"x":0.167,"y":0.167},"t":11,"s":[250,249.358,0],"to":[0,2.349,0],"ti":[0,-6.97,0]},{"i":{"x":0.833,"y":0.833},"o":{"x":0.167,"y":0.167},"t":13,"s":[250,262.023,0],"to":[0,5.359,0],"ti":[0,-4.564,0]},{"i":{"x":0.833,"y":0.833},"o":{"x":0.167,"y":0.167},"t":15,"s":[250,280.675,0],"to":[0,1.743,0],"ti":[0,-1.481,0]},{"i":{"x":0.833,"y":0.833},"o":{"x":0.167,"y":0.167},"t":16,"s":[250,283.506,0],"to":[0,1.96,0],"ti":[0,-1.695,0]},{"i":{"x":0.833,"y":0.833},"o":{"x":0.167,"y":0.167},"t":17,"s":[250,292.003,0],"to":[0,5.712,0],"ti":[0,-1.242,0]},{"i":{"x":0.833,"y":0.833},"o":{"x":0.167,"y":0.167},"t":19,"s":[250,300,0],"to":[0,3.058,0],"ti":[0,2.867,0]},{"i":{"x":0.833,"y":0.833},"o":{"x":0.167,"y":0.167},"t":20,"s":[250,296.857,0],"to":[0,-2.598,0],"ti":[0,3.524,0]},{"i":{"x":0.833,"y":0.833},"o":{"x":0.167,"y":0.167},"t":22,"s":[250,288.291,0],"to":[0,-2.973,0],"ti":[0,0,0]},{"i":{"x":0.833,"y":0.833},"o":{"x":0.167,"y":0.167},"t":23,"s":[250,281,0],"to":[0,0,0],"ti":[0,0,0]},{"i":{"x":0.833,"y":0.833},"o":{"x":0.167,"y":0.167},"t":24,"s":[250,274.994,0],"to":[0,0,0],"ti":[0,0,0]},{"i":{"x":0.833,"y":0.833},"o":{"x":0.167,"y":0.167},"t":25,"s":[250,267.994,0],"to":[0,0,0],"ti":[0,0,0]},{"i":{"x":0.833,"y":0.833},"o":{"x":0.167,"y":0.167},"t":26,"s":[250,261,0],"to":[0,0,0],"ti":[0,0,0]},{"i":{"x":0.833,"y":0.833},"o":{"x":0.167,"y":0.167},"t":27,"s":[250,252.502,0],"to":[0,0,0],"ti":[0,0,0]},{"i":{"x":0.833,"y":0.833},"o":{"x":0.167,"y":0.167},"t":28,"s":[250,248,0],"to":[0,0,0],"ti":[0,0,0]},{"t":29,"s":[250,247,0]}],"ix":2,"l":2},"a":{"a":0,"k":[0,0,0],"ix":1,"l":2},"s":{"a":0,"k":[100,100,100],"ix":6,"l":2}},"ao":0,"shapes":[{"ty":"gr","it":[{"ind":0,"ty":"sh","ix":1,"ks":{"a":1,"k":[{"i":{"x":0.79,"y":1},"o":{"x":0.21,"y":0},"t":0,"s":[{"i":[[-94.654,0],[0,93.823],[94.653,0],[0,-93.823]],"o":[[94.654,0],[0,-93.823],[-94.653,0],[0,93.823]],"v":[[0,170],[171.5,0],[0,-170],[-171.5,0]],"c":true}]},{"i":{"x":0.79,"y":1},"o":{"x":0.21,"y":0},"t":39,"s":[{"i":[[-94.653,0],[0,-94.651],[94.654,0],[0,94.651]],"o":[[94.654,0],[0,94.651],[-94.653,0],[0,-94.651]],"v":[[0,-171.5],[171.5,0],[0,171.5],[-171.5,0]],"c":true}]},{"t":73,"s":[{"i":[[-94.654,0],[0,93.823],[94.653,0],[0,-93.823]],"o":[[94.654,0],[0,-93.823],[-94.653,0],[0,93.823]],"v":[[0,170],[171.5,0],[0,-170],[-171.5,0]],"c":true}]}],"ix":2},"nm":"Path 1","mn":"ADBE Vector Shape - Group","hd":false},{"ty":"st","c":{"a":0,"k":[0,0,0,1],"ix":3},"o":{"a":0,"k":100,"ix":4},"w":{"a":0,"k":16,"ix":5,"x":"var $bm_rt;\n$bm_rt = comp('02 coin').layer('Main Stroke width - Color Ctrl').effect('Stroke width')('Slider');"},"lc":2,"lj":2,"bm":0,"nm":"Stroke 1","mn":"ADBE Vector Graphic - Stroke","hd":false},{"ty":"tr","p":{"a":0,"k":[0,0],"ix":2},"a":{"a":0,"k":[0,0],"ix":1},"s":{"a":0,"k":[100,100],"ix":3},"r":{"a":0,"k":0,"ix":6},"o":{"a":0,"k":100,"ix":7},"sk":{"a":0,"k":0,"ix":4},"sa":{"a":0,"k":0,"ix":5},"nm":"Transform"}],"nm":"Group 3","np":2,"cix":2,"bm":0,"ix":1,"mn":"ADBE Vector Group","hd":false},{"ty":"gr","it":[{"ind":0,"ty":"sh","ix":1,"ks":{"a":1,"k":[{"i":{"x":0.79,"y":1},"o":{"x":0.21,"y":0},"t":0,"s":[{"i":[[0,0],[0,0],[0,0],[0,0]],"o":[[0,0],[0,0],[0,0],[0,0]],"v":[[-45.733,-45.333],[45.733,-45.333],[45.733,45.333],[-45.733,45.333]],"c":true}]},{"i":{"x":0.79,"y":1},"o":{"x":0.21,"y":0},"t":39,"s":[{"i":[[0,0],[0,0],[0,0],[0,0]],"o":[[0,0],[0,0],[0,0],[0,0]],"v":[[-45.733,45.733],[45.733,45.733],[45.733,-45.733],[-45.733,-45.733]],"c":true}]},{"t":73,"s":[{"i":[[0,0],[0,0],[0,0],[0,0]],"o":[[0,0],[0,0],[0,0],[0,0]],"v":[[-45.733,-45.333],[45.733,-45.333],[45.733,45.333],[-45.733,45.333]],"c":true}]}],"ix":2},"nm":"Path 1","mn":"ADBE Vector Shape - Group","hd":false},{"ty":"st","c":{"a":0,"k":[0,0,0,1],"ix":3},"o":{"a":0,"k":100,"ix":4},"w":{"a":0,"k":16,"ix":5,"x":"var $bm_rt;\n$bm_rt = comp('02 coin').layer('Main Stroke width - Color Ctrl').effect('Stroke width')('Slider');"},"lc":2,"lj":2,"bm":0,"nm":"Stroke 1","mn":"ADBE Vector Graphic - Stroke","hd":false},{"ty":"tr","p":{"a":0,"k":[0,0],"ix":2},"a":{"a":0,"k":[0,0],"ix":1},"s":{"a":0,"k":[100,100],"ix":3},"r":{"a":0,"k":0,"ix":6},"o":{"a":0,"k":100,"ix":7},"sk":{"a":0,"k":0,"ix":4},"sa":{"a":0,"k":0,"ix":5},"nm":"Transform"}],"nm":"Group 1","np":2,"cix":2,"bm":0,"ix":2,"mn":"ADBE Vector Group","hd":false},{"ty":"gr","it":[{"ind":0,"ty":"sh","ix":1,"ks":{"a":1,"k":[{"i":{"x":0.79,"y":1},"o":{"x":0.21,"y":0},"t":0,"s":[{"i":[[-69.413,0],[0,68.805],[69.412,0],[0,-68.805]],"o":[[69.413,0],[0,-68.805],[-69.412,0],[0,68.805]],"v":[[0,124.667],[125.767,0],[0,-124.667],[-125.767,0]],"c":true}]},{"i":{"x":0.79,"y":1},"o":{"x":0.21,"y":0},"t":39,"s":[{"i":[[-69.412,0],[0,-69.412],[69.413,0],[0,69.412]],"o":[[69.413,0],[0,69.412],[-69.412,0],[0,-69.412]],"v":[[0,-125.767],[125.767,0],[0,125.767],[-125.767,0]],"c":true}]},{"t":73,"s":[{"i":[[-69.413,0],[0,68.805],[69.412,0],[0,-68.805]],"o":[[69.413,0],[0,-68.805],[-69.412,0],[0,68.805]],"v":[[0,124.667],[125.767,0],[0,-124.667],[-125.767,0]],"c":true}]}],"ix":2},"nm":"Path 1","mn":"ADBE Vector Shape - Group","hd":false},{"ty":"st","c":{"a":0,"k":[0.20000000298,0.800000011921,0.800000011921,1],"ix":3},"o":{"a":0,"k":100,"ix":4},"w":{"a":0,"k":16,"ix":5,"x":"var $bm_rt;\n$bm_rt = comp('02 coin').layer('Main Stroke width - Color Ctrl').effect('Stroke width')('Slider');"},"lc":2,"lj":2,"bm":0,"nm":"Stroke 1","mn":"ADBE Vector Graphic - Stroke","hd":false},{"ty":"tr","p":{"a":0,"k":[0,0],"ix":2},"a":{"a":0,"k":[0,0],"ix":1},"s":{"a":0,"k":[100,100],"ix":3},"r":{"a":0,"k":0,"ix":6},"o":{"a":0,"k":100,"ix":7},"sk":{"a":0,"k":0,"ix":4},"sa":{"a":0,"k":0,"ix":5},"nm":"Transform"}],"nm":"Group 2","np":2,"cix":2,"bm":0,"ix":3,"mn":"ADBE Vector Group","hd":false},{"ty":"fl","c":{"a":0,"k":[1,0,0,1],"ix":4},"o":{"a":0,"k":100,"ix":5},"r":1,"bm":0,"nm":"Fill 1","mn":"ADBE Vector Graphic - Fill","hd":false}],"ip":0,"op":40,"st":0,"ct":1,"bm":0},{"ddd":0,"ind":8,"ty":4,"nm":"coin 2","tt":2,"tp":7,"sr":1,"ks":{"o":{"a":0,"k":100,"ix":11},"r":{"a":0,"k":0,"ix":10},"p":{"a":1,"k":[{"i":{"x":0.833,"y":0.833},"o":{"x":0.167,"y":0.167},"t":0,"s":[250,250,0],"to":[0,11,0],"ti":[0,0,0]},{"i":{"x":0.833,"y":0.833},"o":{"x":0.167,"y":0.167},"t":19,"s":[250,316,0],"to":[0,0,0],"ti":[0,0,0]},{"i":{"x":0.833,"y":0.833},"o":{"x":0.167,"y":0.167},"t":39,"s":[250,250,0],"to":[0,0,0],"ti":[0,0,0]},{"i":{"x":0.833,"y":0.833},"o":{"x":0.167,"y":0.167},"t":56,"s":[250,316,0],"to":[0,0,0],"ti":[0,11,0]},{"t":73,"s":[250,250,0]}],"ix":2,"l":2},"a":{"a":0,"k":[0,0,0],"ix":1,"l":2},"s":{"a":0,"k":[100,100,100],"ix":6,"l":2}},"ao":0,"shapes":[{"ty":"gr","it":[{"ty":"rc","d":1,"s":{"a":0,"k":[482,472],"ix":2},"p":{"a":0,"k":[0,0],"ix":3},"r":{"a":0,"k":0,"ix":4},"nm":"Rectangle Path 1","mn":"ADBE Vector Shape - Rect","hd":false},{"ty":"st","c":{"a":0,"k":[0,0,0,1],"ix":3},"o":{"a":0,"k":0,"ix":4},"w":{"a":0,"k":16,"ix":5},"lc":1,"lj":1,"ml":4,"bm":0,"nm":"Stroke 1","mn":"ADBE Vector Graphic - Stroke","hd":false},{"ty":"tr","p":{"a":0,"k":[-1,-4],"ix":2},"a":{"a":0,"k":[0,0],"ix":1},"s":{"a":0,"k":[100,100],"ix":3},"r":{"a":0,"k":0,"ix":6},"o":{"a":0,"k":100,"ix":7},"sk":{"a":0,"k":0,"ix":4},"sa":{"a":0,"k":0,"ix":5},"nm":"Transform"}],"nm":"Rectangle 1","np":3,"cix":2,"bm":0,"ix":1,"mn":"ADBE Vector Group","hd":false},{"ty":"gr","it":[{"ind":0,"ty":"sh","ix":1,"ks":{"a":1,"k":[{"i":{"x":0.79,"y":1},"o":{"x":0.21,"y":0},"t":0,"s":[{"i":[[-94.654,0],[0,93.823],[94.653,0],[0,-93.823]],"o":[[94.654,0],[0,-93.823],[-94.653,0],[0,93.823]],"v":[[0,170],[171.5,0],[0,-170],[-171.5,0]],"c":true}]},{"i":{"x":0.79,"y":1},"o":{"x":0.21,"y":0},"t":39,"s":[{"i":[[-94.653,0],[0,-94.651],[94.654,0],[0,94.651]],"o":[[94.654,0],[0,94.651],[-94.653,0],[0,-94.651]],"v":[[0,-171.5],[171.5,0],[0,171.5],[-171.5,0]],"c":true}]},{"t":73,"s":[{"i":[[-94.654,0],[0,93.823],[94.653,0],[0,-93.823]],"o":[[94.654,0],[0,-93.823],[-94.653,0],[0,93.823]],"v":[[0,170],[171.5,0],[0,-170],[-171.5,0]],"c":true}]}],"ix":2},"nm":"Path 1","mn":"ADBE Vector Shape - Group","hd":false},{"ty":"st","c":{"a":0,"k":[0,0,0,1],"ix":3,"x":"var $bm_rt;\n$bm_rt = comp('02 coin').layer('Main Stroke width - Color Ctrl').effect('Base Color')('Color');"},"o":{"a":0,"k":100,"ix":4},"w":{"a":0,"k":16,"ix":5,"x":"var $bm_rt;\n$bm_rt = comp('02 coin').layer('Main Stroke width - Color Ctrl').effect('Stroke width')('Slider');"},"lc":2,"lj":2,"bm":0,"nm":"Stroke 1","mn":"ADBE Vector Graphic - Stroke","hd":false},{"ty":"tr","p":{"a":0,"k":[0,0],"ix":2},"a":{"a":0,"k":[0,0],"ix":1},"s":{"a":0,"k":[100,100],"ix":3},"r":{"a":0,"k":0,"ix":6},"o":{"a":0,"k":100,"ix":7},"sk":{"a":0,"k":0,"ix":4},"sa":{"a":0,"k":0,"ix":5},"nm":"Transform"}],"nm":"Group 3","np":2,"cix":2,"bm":0,"ix":2,"mn":"ADBE Vector Group","hd":false}],"ip":0,"op":40,"st":0,"ct":1,"bm":0},{"ddd":0,"ind":9,"ty":4,"nm":"coin","sr":1,"ks":{"o":{"a":0,"k":100,"ix":11},"r":{"a":0,"k":0,"ix":10},"p":{"a":0,"k":[250,250,0],"ix":2,"l":2},"a":{"a":0,"k":[0,0,0],"ix":1,"l":2},"s":{"a":0,"k":[100,100,100],"ix":6,"l":2}},"ao":0,"shapes":[{"ty":"gr","it":[{"ind":0,"ty":"sh","ix":1,"ks":{"a":1,"k":[{"i":{"x":0.79,"y":1},"o":{"x":0.21,"y":0},"t":0,"s":[{"i":[[0,0],[0,0],[0,0],[0,0]],"o":[[0,0],[0,0],[0,0],[0,0]],"v":[[-45.733,-45.333],[45.733,-45.333],[45.733,45.333],[-45.733,45.333]],"c":true}]},{"i":{"x":0.79,"y":1},"o":{"x":0.21,"y":0},"t":39,"s":[{"i":[[0,0],[0,0],[0,0],[0,0]],"o":[[0,0],[0,0],[0,0],[0,0]],"v":[[-45.733,45.733],[45.733,45.733],[45.733,-45.733],[-45.733,-45.733]],"c":true}]},{"t":73,"s":[{"i":[[0,0],[0,0],[0,0],[0,0]],"o":[[0,0],[0,0],[0,0],[0,0]],"v":[[-45.733,-45.333],[45.733,-45.333],[45.733,45.333],[-45.733,45.333]],"c":true}]}],"ix":2},"nm":"Path 1","mn":"ADBE Vector Shape - Group","hd":false},{"ty":"st","c":{"a":0,"k":[0,0,0,1],"ix":3,"x":"var $bm_rt;\n$bm_rt = comp('02 coin').layer('Main Stroke width - Color Ctrl').effect('Base Color')('Color');"},"o":{"a":0,"k":100,"ix":4},"w":{"a":0,"k":16,"ix":5,"x":"var $bm_rt;\n$bm_rt = comp('02 coin').layer('Main Stroke width - Color Ctrl').effect('Stroke width')('Slider');"},"lc":2,"lj":2,"bm":0,"nm":"Stroke 1","mn":"ADBE Vector Graphic - Stroke","hd":false},{"ty":"fl","c":{"a":0,"k":[1,1,1,1],"ix":4},"o":{"a":0,"k":100,"ix":5},"r":1,"bm":0,"nm":"Fill 1","mn":"ADBE Vector Graphic - Fill","hd":false},{"ty":"tr","p":{"a":0,"k":[0,0],"ix":2},"a":{"a":0,"k":[0,0],"ix":1},"s":{"a":0,"k":[100,100],"ix":3},"r":{"a":0,"k":0,"ix":6},"o":{"a":0,"k":100,"ix":7},"sk":{"a":0,"k":0,"ix":4},"sa":{"a":0,"k":0,"ix":5},"nm":"Transform"}],"nm":"Group 1","np":3,"cix":2,"bm":0,"ix":1,"mn":"ADBE Vector Group","hd":false},{"ty":"gr","it":[{"ind":0,"ty":"sh","ix":1,"ks":{"a":1,"k":[{"i":{"x":0.79,"y":1},"o":{"x":0.21,"y":0},"t":0,"s":[{"i":[[-69.413,0],[0,68.805],[69.412,0],[0,-68.805]],"o":[[69.413,0],[0,-68.805],[-69.412,0],[0,68.805]],"v":[[0,124.667],[125.767,0],[0,-124.667],[-125.767,0]],"c":true}]},{"i":{"x":0.79,"y":1},"o":{"x":0.21,"y":0},"t":39,"s":[{"i":[[-69.412,0],[0,-69.412],[69.413,0],[0,69.412]],"o":[[69.413,0],[0,69.412],[-69.412,0],[0,-69.412]],"v":[[0,-125.767],[125.767,0],[0,125.767],[-125.767,0]],"c":true}]},{"t":73,"s":[{"i":[[-69.413,0],[0,68.805],[69.412,0],[0,-68.805]],"o":[[69.413,0],[0,-68.805],[-69.412,0],[0,68.805]],"v":[[0,124.667],[125.767,0],[0,-124.667],[-125.767,0]],"c":true}]}],"ix":2},"nm":"Path 1","mn":"ADBE Vector Shape - Group","hd":false},{"ty":"st","c":{"a":0,"k":[0.20000000298,0.800000011921,0.800000011921,1],"ix":3,"x":"var $bm_rt;\n$bm_rt = comp('02 coin').layer('Main Stroke width - Color Ctrl').effect('Base Color')('Color');"},"o":{"a":0,"k":100,"ix":4},"w":{"a":0,"k":16,"ix":5,"x":"var $bm_rt;\n$bm_rt = comp('02 coin').layer('Main Stroke width - Color Ctrl').effect('Stroke width')('Slider');"},"lc":2,"lj":2,"bm":0,"nm":"Stroke 1","mn":"ADBE Vector Graphic - Stroke","hd":false},{"ty":"fl","c":{"a":0,"k":[0.992156862745,0.796078431373,0.313725490196,1],"ix":4},"o":{"a":0,"k":100,"ix":5},"r":1,"bm":0,"nm":"Fill 1","mn":"ADBE Vector Graphic - Fill","hd":false},{"ty":"tr","p":{"a":0,"k":[0,0],"ix":2},"a":{"a":0,"k":[0,0],"ix":1},"s":{"a":0,"k":[100,100],"ix":3},"r":{"a":0,"k":0,"ix":6},"o":{"a":0,"k":100,"ix":7},"sk":{"a":0,"k":0,"ix":4},"sa":{"a":0,"k":0,"ix":5},"nm":"Transform"}],"nm":"Group 2","np":3,"cix":2,"bm":0,"ix":2,"mn":"ADBE Vector Group","hd":false},{"ty":"gr","it":[{"ind":0,"ty":"sh","ix":1,"ks":{"a":1,"k":[{"i":{"x":0.79,"y":1},"o":{"x":0.21,"y":0},"t":0,"s":[{"i":[[-94.654,0],[0,93.823],[94.653,0],[0,-93.823]],"o":[[94.654,0],[0,-93.823],[-94.653,0],[0,93.823]],"v":[[0,170],[171.5,0],[0,-170],[-171.5,0]],"c":true}]},{"i":{"x":0.79,"y":1},"o":{"x":0.21,"y":0},"t":39,"s":[{"i":[[-94.653,0],[0,-94.651],[94.654,0],[0,94.651]],"o":[[94.654,0],[0,94.651],[-94.653,0],[0,-94.651]],"v":[[0,-171.5],[171.5,0],[0,171.5],[-171.5,0]],"c":true}]},{"t":73,"s":[{"i":[[-94.654,0],[0,93.823],[94.653,0],[0,-93.823]],"o":[[94.654,0],[0,-93.823],[-94.653,0],[0,93.823]],"v":[[0,170],[171.5,0],[0,-170],[-171.5,0]],"c":true}]}],"ix":2},"nm":"Path 1","mn":"ADBE Vector Shape - Group","hd":false},{"ty":"st","c":{"a":0,"k":[0,0,0,1],"ix":3,"x":"var $bm_rt;\n$bm_rt = comp('02 coin').layer('Main Stroke width - Color Ctrl').effect('Base Color')('Color');"},"o":{"a":0,"k":100,"ix":4},"w":{"a":0,"k":16,"ix":5,"x":"var $bm_rt;\n$bm_rt = comp('02 coin').layer('Main Stroke width - Color Ctrl').effect('Stroke width')('Slider');"},"lc":2,"lj":2,"bm":0,"nm":"Stroke 1","mn":"ADBE Vector Graphic - Stroke","hd":false},{"ty":"fl","c":{"a":0,"k":[0.992156862745,0.560784313725,0.003921568627,1],"ix":4},"o":{"a":0,"k":100,"ix":5},"r":1,"bm":0,"nm":"Fill 1","mn":"ADBE Vector Graphic - Fill","hd":false},{"ty":"tr","p":{"a":0,"k":[0,0],"ix":2},"a":{"a":0,"k":[0,0],"ix":1},"s":{"a":0,"k":[100,100],"ix":3},"r":{"a":0,"k":0,"ix":6},"o":{"a":0,"k":100,"ix":7},"sk":{"a":0,"k":0,"ix":4},"sa":{"a":0,"k":0,"ix":5},"nm":"Transform"}],"nm":"Group 3","np":3,"cix":2,"bm":0,"ix":3,"mn":"ADBE Vector Group","hd":false}],"ip":0,"op":40,"st":0,"ct":1,"bm":0},{"ddd":0,"ind":10,"ty":4,"nm":"coin 9","sr":1,"ks":{"o":{"a":0,"k":100,"ix":11},"r":{"a":0,"k":0,"ix":10},"p":{"a":1,"k":[{"i":{"x":0.71,"y":1},"o":{"x":0.29,"y":0},"t":25,"s":[250,250,0],"to":[0,-15,0],"ti":[0,15,0]},{"t":39,"s":[250,160,0]}],"ix":2,"l":2},"a":{"a":0,"k":[0,0,0],"ix":1,"l":2},"s":{"a":0,"k":[100,100,100],"ix":6,"l":2}},"ao":0,"shapes":[{"ty":"gr","it":[{"ind":0,"ty":"sh","ix":1,"ks":{"a":1,"k":[{"i":{"x":0.79,"y":1},"o":{"x":0.21,"y":0},"t":0,"s":[{"i":[[0,0],[0,0]],"o":[[0,0],[0,0]],"v":[[-45.733,-45.333],[45.733,-45.333]],"c":true}]},{"i":{"x":0.79,"y":1},"o":{"x":0.21,"y":0},"t":39,"s":[{"i":[[0,0],[0,0]],"o":[[0,0],[0,0]],"v":[[-45.733,45.733],[45.733,45.733]],"c":true}]},{"t":73,"s":[{"i":[[0,0],[0,0]],"o":[[0,0],[0,0]],"v":[[-45.733,-45.333],[45.733,-45.333]],"c":true}]}],"ix":2},"nm":"Path 1","mn":"ADBE Vector Shape - Group","hd":false},{"ty":"st","c":{"a":0,"k":[0,0,0,1],"ix":3,"x":"var $bm_rt;\n$bm_rt = comp('02 coin').layer('Main Stroke width - Color Ctrl').effect('Base Color')('Color');"},"o":{"a":0,"k":100,"ix":4},"w":{"a":0,"k":16,"ix":5,"x":"var $bm_rt;\n$bm_rt = comp('02 coin').layer('Main Stroke width - Color Ctrl').effect('Stroke width')('Slider');"},"lc":2,"lj":2,"bm":0,"nm":"Stroke 1","mn":"ADBE Vector Graphic - Stroke","hd":false},{"ty":"tr","p":{"a":0,"k":[0,0],"ix":2},"a":{"a":0,"k":[0,0],"ix":1},"s":{"a":0,"k":[100,100],"ix":3},"r":{"a":0,"k":0,"ix":6},"o":{"a":0,"k":100,"ix":7},"sk":{"a":0,"k":0,"ix":4},"sa":{"a":0,"k":0,"ix":5},"nm":"Transform"}],"nm":"Group 1","np":2,"cix":2,"bm":0,"ix":1,"mn":"ADBE Vector Group","hd":false}],"ip":0,"op":39,"st":0,"ct":1,"bm":0},{"ddd":0,"ind":11,"ty":4,"nm":"coin 8","sr":1,"ks":{"o":{"a":0,"k":100,"ix":11},"r":{"a":0,"k":0,"ix":10},"p":{"a":1,"k":[{"i":{"x":0.71,"y":1},"o":{"x":0.29,"y":0},"t":0,"s":[250,250,0],"to":[0,6.167,0],"ti":[0,-6.167,0]},{"t":13,"s":[250,287,0]}],"ix":2,"l":2},"a":{"a":0,"k":[0,0,0],"ix":1,"l":2},"s":{"a":0,"k":[100,100,100],"ix":6,"l":2}},"ao":0,"shapes":[{"ty":"gr","it":[{"ind":0,"ty":"sh","ix":1,"ks":{"a":1,"k":[{"i":{"x":0.79,"y":1},"o":{"x":0.21,"y":0},"t":0,"s":[{"i":[[0,0],[0,0]],"o":[[0,0],[0,0]],"v":[[-45.733,-45.333],[45.733,-45.333]],"c":true}]},{"i":{"x":0.79,"y":1},"o":{"x":0.21,"y":0},"t":39,"s":[{"i":[[0,0],[0,0]],"o":[[0,0],[0,0]],"v":[[-45.733,45.733],[45.733,45.733]],"c":true}]},{"t":73,"s":[{"i":[[0,0],[0,0]],"o":[[0,0],[0,0]],"v":[[-45.733,-45.333],[45.733,-45.333]],"c":true}]}],"ix":2},"nm":"Path 1","mn":"ADBE Vector Shape - Group","hd":false},{"ty":"st","c":{"a":0,"k":[0,0,0,1],"ix":3,"x":"var $bm_rt;\n$bm_rt = comp('02 coin').layer('Main Stroke width - Color Ctrl').effect('Base Color')('Color');"},"o":{"a":0,"k":100,"ix":4},"w":{"a":0,"k":16,"ix":5,"x":"var $bm_rt;\n$bm_rt = comp('02 coin').layer('Main Stroke width - Color Ctrl').effect('Stroke width')('Slider');"},"lc":2,"lj":2,"bm":0,"nm":"Stroke 1","mn":"ADBE Vector Graphic - Stroke","hd":false},{"ty":"tr","p":{"a":0,"k":[0,0],"ix":2},"a":{"a":0,"k":[0,0],"ix":1},"s":{"a":0,"k":[100,100],"ix":3},"r":{"a":0,"k":0,"ix":6},"o":{"a":0,"k":100,"ix":7},"sk":{"a":0,"k":0,"ix":4},"sa":{"a":0,"k":0,"ix":5},"nm":"Transform"}],"nm":"Group 1","np":2,"cix":2,"bm":0,"ix":1,"mn":"ADBE Vector Group","hd":false}],"ip":0,"op":13,"st":0,"ct":1,"bm":0},{"ddd":0,"ind":12,"ty":4,"nm":"coin 11","parent":4,"sr":1,"ks":{"o":{"a":0,"k":100,"ix":11},"r":{"a":0,"k":0,"ix":10},"p":{"a":1,"k":[{"i":{"x":0.71,"y":1},"o":{"x":0.29,"y":0},"t":61,"s":[0,1,0],"to":[0,14.833,0],"ti":[0,-14.833,0]},{"t":73,"s":[0,90,0]}],"ix":2,"l":2},"a":{"a":0,"k":[0,0,0],"ix":1,"l":2},"s":{"a":0,"k":[100,100,100],"ix":6,"l":2}},"ao":0,"shapes":[{"ty":"gr","it":[{"ind":0,"ty":"sh","ix":1,"ks":{"a":1,"k":[{"i":{"x":0.79,"y":1},"o":{"x":0.21,"y":0},"t":0,"s":[{"i":[[0,0],[0,0]],"o":[[0,0],[0,0]],"v":[[-45.733,-45.333],[45.733,-45.333]],"c":true}]},{"i":{"x":0.79,"y":1},"o":{"x":0.21,"y":0},"t":39,"s":[{"i":[[0,0],[0,0]],"o":[[0,0],[0,0]],"v":[[-45.733,45.733],[45.733,45.733]],"c":true}]},{"t":73,"s":[{"i":[[0,0],[0,0]],"o":[[0,0],[0,0]],"v":[[-45.733,-45.333],[45.733,-45.333]],"c":true}]}],"ix":2},"nm":"Path 1","mn":"ADBE Vector Shape - Group","hd":false},{"ty":"st","c":{"a":0,"k":[0,0,0,1],"ix":3,"x":"var $bm_rt;\n$bm_rt = comp('02 coin').layer('Main Stroke width - Color Ctrl').effect('Base Color')('Color');"},"o":{"a":0,"k":100,"ix":4},"w":{"a":0,"k":16,"ix":5,"x":"var $bm_rt;\n$bm_rt = comp('02 coin').layer('Main Stroke width - Color Ctrl').effect('Stroke width')('Slider');"},"lc":2,"lj":2,"bm":0,"nm":"Stroke 1","mn":"ADBE Vector Graphic - Stroke","hd":false},{"ty":"tr","p":{"a":0,"k":[0,0],"ix":2},"a":{"a":0,"k":[0,0],"ix":1},"s":{"a":0,"k":[100,100],"ix":3},"r":{"a":0,"k":0,"ix":6},"o":{"a":0,"k":100,"ix":7},"sk":{"a":0,"k":0,"ix":4},"sa":{"a":0,"k":0,"ix":5},"nm":"Transform"}],"nm":"Group 1","np":2,"cix":2,"bm":0,"ix":1,"mn":"ADBE Vector Group","hd":false}],"ip":56,"op":75,"st":0,"ct":1,"bm":0},{"ddd":0,"ind":13,"ty":4,"nm":"back 2","sr":1,"ks":{"o":{"a":0,"k":100,"ix":11},"r":{"a":0,"k":0,"ix":10},"p":{"a":0,"k":[250,250,0],"ix":2,"l":2},"a":{"a":0,"k":[0,0,0],"ix":1,"l":2},"s":{"a":0,"k":[100,100,100],"ix":6,"l":2}},"ao":0,"shapes":[{"ty":"gr","it":[{"ind":0,"ty":"sh","ix":1,"ks":{"a":1,"k":[{"i":{"x":0.833,"y":0.833},"o":{"x":0.333,"y":0},"t":39,"s":[{"i":[[0,0],[159.748,3.489],[0,0],[0,0],[-126.006,1.026],[0,0]],"o":[[0,0],[-165.213,-3.609],[0,0],[0,0],[126.006,-1.026],[0,0]],"v":[[171,3],[3.252,-170.489],[-174,2],[-162,61],[3.994,70.026],[159,62]],"c":true}]},{"i":{"x":0.667,"y":1},"o":{"x":0.167,"y":0.167},"t":56,"s":[{"i":[[0,0],[153.252,1.511],[0,0],[0,0],[-126.006,1.026],[0,0]],"o":[[0,0],[-153.252,-1.511],[0,0],[0,0],[126.006,-1.026],[0,0]],"v":[[171,3],[2.252,2.511],[-174,2],[-171,66],[3.994,70.026],[172,66]],"c":true}]},{"t":73,"s":[{"i":[[0,0],[159.748,3.489],[0,0],[0,0],[-126.006,1.026],[0,0]],"o":[[0,0],[-165.213,-3.609],[0,0],[0,0],[126.006,-1.026],[0,0]],"v":[[171,3],[3.252,-170.489],[-174,2],[-162,61],[3.994,70.026],[159,62]],"c":true}]}],"ix":2},"nm":"Path 1","mn":"ADBE Vector Shape - Group","hd":false},{"ty":"fl","c":{"a":0,"k":[0.992156922583,0.560784313725,0.003921568627,1],"ix":4},"o":{"a":0,"k":100,"ix":5},"r":1,"bm":0,"nm":"Fill 1","mn":"ADBE Vector Graphic - Fill","hd":false},{"ty":"tr","p":{"a":0,"k":[0,0],"ix":2},"a":{"a":0,"k":[0,0],"ix":1},"s":{"a":0,"k":[100,100],"ix":3},"r":{"a":0,"k":0,"ix":6},"o":{"a":0,"k":100,"ix":7},"sk":{"a":0,"k":0,"ix":4},"sa":{"a":0,"k":0,"ix":5},"nm":"Transform"}],"nm":"Shape 1","np":3,"cix":2,"bm":0,"ix":1,"mn":"ADBE Vector Group","hd":false}],"ip":39,"op":120,"st":0,"ct":1,"bm":0},{"ddd":0,"ind":14,"ty":4,"nm":"back","sr":1,"ks":{"o":{"a":0,"k":100,"ix":11},"r":{"a":0,"k":0,"ix":10},"p":{"a":0,"k":[250,250,0],"ix":2,"l":2},"a":{"a":0,"k":[0,0,0],"ix":1,"l":2},"s":{"a":0,"k":[100,100,100],"ix":6,"l":2}},"ao":0,"shapes":[{"ty":"gr","it":[{"ind":0,"ty":"sh","ix":1,"ks":{"a":1,"k":[{"i":{"x":0.833,"y":0.833},"o":{"x":0.333,"y":0},"t":0,"s":[{"i":[[0,0],[133.001,0.507],[0,0],[0,0],[-125.961,3.529],[0,0]],"o":[[0,0],[-133.001,-0.507],[0,0],[0,0],[108.012,-3.026],[0,0]],"v":[[171,3],[1.001,2.507],[-174,2],[-157,69],[3.988,169.026],[162,71]],"c":true}]},{"i":{"x":0.667,"y":1},"o":{"x":0.167,"y":0.167},"t":19,"s":[{"i":[[0,0],[0,0],[0,0],[0,0],[-126.006,1.026],[0,0]],"o":[[0,0],[0,0],[0,0],[0,0],[126.006,-1.026],[0,0]],"v":[[171,3],[2.252,2.511],[-174,2],[-171,66],[3.994,70.026],[172,66]],"c":true}]},{"t":39,"s":[{"i":[[0,0],[0,0],[0,0],[0,0],[-125.961,3.529],[0,0]],"o":[[0,0],[0,0],[0,0],[0,0],[108.012,-3.026],[0,0]],"v":[[171,3],[2.252,2.511],[-174,2],[-157,69],[3.988,169.026],[162,71]],"c":true}]}],"ix":2},"nm":"Path 1","mn":"ADBE Vector Shape - Group","hd":false},{"ty":"fl","c":{"a":0,"k":[0.992156922583,0.560784313725,0.003921568627,1],"ix":4},"o":{"a":0,"k":100,"ix":5},"r":1,"bm":0,"nm":"Fill 1","mn":"ADBE Vector Graphic - Fill","hd":false},{"ty":"tr","p":{"a":0,"k":[0,0],"ix":2},"a":{"a":0,"k":[0,0],"ix":1},"s":{"a":0,"k":[100,100],"ix":3},"r":{"a":0,"k":0,"ix":6},"o":{"a":0,"k":100,"ix":7},"sk":{"a":0,"k":0,"ix":4},"sa":{"a":0,"k":0,"ix":5},"nm":"Transform"}],"nm":"Shape 1","np":3,"cix":2,"bm":0,"ix":1,"mn":"ADBE Vector Group","hd":false}],"ip":0,"op":39,"st":0,"ct":1,"bm":0}]}],"layers":[{"ddd":0,"ind":1,"ty":3,"nm":"Main Stroke width - Color Ctrl","sr":1,"ks":{"o":{"a":0,"k":0,"ix":11},"r":{"a":0,"k":0,"ix":10},"p":{"a":0,"k":[250,250,0],"ix":2,"l":2},"a":{"a":0,"k":[50,50,0],"ix":1,"l":2},"s":{"a":0,"k":[100,100,100],"ix":6,"l":2}},"ao":0,"ef":[{"ty":5,"nm":"Stroke width","np":3,"mn":"ADBE Slider Control","ix":1,"en":1,"ef":[{"ty":0,"nm":"Slider","mn":"ADBE Slider Control-0001","ix":1,"v":{"a":0,"k":16,"ix":1}}]},{"ty":5,"nm":"Stroke width details","np":3,"mn":"ADBE Slider Control","ix":2,"en":1,"ef":[{"ty":0,"nm":"Slider","mn":"ADBE Slider Control-0001","ix":1,"v":{"a":0,"k":12,"ix":1}}]},{"ty":5,"nm":"Base Color","np":3,"mn":"ADBE Color Control","ix":3,"en":1,"ef":[{"ty":2,"nm":"Color","mn":"ADBE Color Control-0001","ix":1,"v":{"a":0,"k":[0.019607843831,0.164705887437,0.458823531866,1],"ix":1}}]},{"ty":5,"nm":"Highlight","np":3,"mn":"ADBE Color Control","ix":4,"en":1,"ef":[{"ty":2,"nm":"Color","mn":"ADBE Color Control-0001","ix":1,"v":{"a":0,"k":[0.992156863213,0.796078443527,0.313725501299,1],"ix":1}}]}],"ip":0,"op":180,"st":0,"bm":0},{"ddd":0,"ind":2,"ty":4,"nm":"Star 2","parent":5,"sr":1,"ks":{"o":{"a":0,"k":100,"ix":11},"r":{"a":0,"k":0,"ix":10},"p":{"a":0,"k":[173.695,166.078,0],"ix":2,"l":2},"a":{"a":0,"k":[-168.305,-106.922,0],"ix":1,"l":2},"s":{"a":0,"k":[100,100,100],"ix":6,"l":2}},"ao":0,"shapes":[{"ty":"gr","it":[{"ind":0,"ty":"sh","ix":1,"ks":{"a":1,"k":[{"i":{"x":0.7,"y":1},"o":{"x":0.3,"y":0},"t":16,"s":[{"i":[[0.168,0],[0,-0.168],[-0.168,0],[0,0.168]],"o":[[0.168,0],[0,-0.168],[-0.168,0],[0,0.168]],"v":[[-168.609,-106.922],[-168.305,-106.618],[-168,-106.922],[-168.305,-107.227]],"c":true}]},{"i":{"x":0.7,"y":1},"o":{"x":0.3,"y":0},"t":28,"s":[{"i":[[28.887,0],[0,-28.887],[-28.887,0],[0,28.887]],"o":[[28.887,0],[0,-28.887],[-28.887,0],[0,28.887]],"v":[[-220.609,-106.922],[-168.305,-54.618],[-116,-106.922],[-168.305,-159.227]],"c":true}]},{"i":{"x":0.7,"y":1},"o":{"x":0.3,"y":0},"t":37,"s":[{"i":[[21.671,0],[0,-21.671],[-21.671,0],[0,21.671]],"o":[[21.671,0],[0,-21.671],[-21.671,0],[0,21.671]],"v":[[-207.543,-106.922],[-168.305,-67.683],[-129.066,-106.922],[-168.305,-146.161]],"c":true}]},{"i":{"x":0.7,"y":1},"o":{"x":0.3,"y":0},"t":51,"s":[{"i":[[21.671,0],[0,-21.671],[-21.671,0],[0,21.671]],"o":[[21.671,0],[0,-21.671],[-21.671,0],[0,21.671]],"v":[[-207.543,-106.922],[-168.305,-67.683],[-129.066,-106.922],[-168.305,-146.161]],"c":true}]},{"i":{"x":0.7,"y":1},"o":{"x":0.3,"y":0},"t":63,"s":[{"i":[[28.887,0],[0,-28.887],[-28.887,0],[0,28.887]],"o":[[28.887,0],[0,-28.887],[-28.887,0],[0,28.887]],"v":[[-220.609,-106.922],[-168.305,-54.618],[-116,-106.922],[-168.305,-159.227]],"c":true}]},{"t":76,"s":[{"i":[[0.168,0],[0,-0.168],[-0.168,0],[0,0.168]],"o":[[0.168,0],[0,-0.168],[-0.168,0],[0,0.168]],"v":[[-168.609,-106.922],[-168.305,-106.618],[-168,-106.922],[-168.305,-107.227]],"c":true}]}],"ix":2},"nm":"Path 1","mn":"ADBE Vector Shape - Group","hd":false},{"ty":"st","c":{"a":0,"k":[0.20000000298,0.800000011921,0.800000011921,1],"ix":3,"x":"var $bm_rt;\n$bm_rt = thisComp.layer('Main Stroke width - Color Ctrl').effect('Highlight')('Color');"},"o":{"a":0,"k":100,"ix":4},"w":{"a":0,"k":16,"ix":5,"x":"var $bm_rt;\n$bm_rt = thisComp.layer('Main Stroke width - Color Ctrl').effect('Stroke width')('Slider');"},"lc":2,"lj":2,"bm":0,"nm":"Stroke 1","mn":"ADBE Vector Graphic - Stroke","hd":false},{"ty":"tr","p":{"a":0,"k":[0,0],"ix":2},"a":{"a":0,"k":[0,0],"ix":1},"s":{"a":0,"k":[100,100],"ix":3},"r":{"a":0,"k":0,"ix":6},"o":{"a":0,"k":100,"ix":7},"sk":{"a":0,"k":0,"ix":4},"sa":{"a":0,"k":0,"ix":5},"nm":"Transform"}],"nm":"Group 1","np":3,"cix":2,"bm":0,"ix":1,"mn":"ADBE Vector Group","hd":false}],"ip":16,"op":76,"st":16,"ct":1,"bm":0},{"ddd":0,"ind":3,"ty":4,"nm":"Star","parent":5,"sr":1,"ks":{"o":{"a":0,"k":100,"ix":11},"r":{"a":0,"k":0,"ix":10},"p":{"a":0,"k":[-170.305,-169.922,0],"ix":2,"l":2},"a":{"a":0,"k":[-168.305,-106.922,0],"ix":1,"l":2},"s":{"a":0,"k":[100,100,100],"ix":6,"l":2}},"ao":0,"shapes":[{"ty":"gr","it":[{"ind":0,"ty":"sh","ix":1,"ks":{"a":1,"k":[{"i":{"x":0.7,"y":1},"o":{"x":0.3,"y":0},"t":3,"s":[{"i":[[0.168,0],[0,-0.168],[-0.168,0],[0,0.168]],"o":[[0.168,0],[0,-0.168],[-0.168,0],[0,0.168]],"v":[[-168.609,-106.922],[-168.305,-106.618],[-168,-106.922],[-168.305,-107.227]],"c":true}]},{"i":{"x":0.7,"y":1},"o":{"x":0.3,"y":0},"t":15,"s":[{"i":[[28.887,0],[0,-28.887],[-28.887,0],[0,28.887]],"o":[[28.887,0],[0,-28.887],[-28.887,0],[0,28.887]],"v":[[-220.609,-106.922],[-168.305,-54.618],[-116,-106.922],[-168.305,-159.227]],"c":true}]},{"i":{"x":0.7,"y":1},"o":{"x":0.3,"y":0},"t":24,"s":[{"i":[[21.671,0],[0,-21.671],[-21.671,0],[0,21.671]],"o":[[21.671,0],[0,-21.671],[-21.671,0],[0,21.671]],"v":[[-207.543,-106.922],[-168.305,-67.683],[-129.066,-106.922],[-168.305,-146.161]],"c":true}]},{"i":{"x":0.7,"y":1},"o":{"x":0.3,"y":0},"t":39,"s":[{"i":[[21.671,0],[0,-21.671],[-21.671,0],[0,21.671]],"o":[[21.671,0],[0,-21.671],[-21.671,0],[0,21.671]],"v":[[-207.543,-106.922],[-168.305,-67.683],[-129.066,-106.922],[-168.305,-146.161]],"c":true}]},{"i":{"x":0.7,"y":1},"o":{"x":0.3,"y":0},"t":51,"s":[{"i":[[28.887,0],[0,-28.887],[-28.887,0],[0,28.887]],"o":[[28.887,0],[0,-28.887],[-28.887,0],[0,28.887]],"v":[[-220.609,-106.922],[-168.305,-54.618],[-116,-106.922],[-168.305,-159.227]],"c":true}]},{"t":64,"s":[{"i":[[0.168,0],[0,-0.168],[-0.168,0],[0,0.168]],"o":[[0.168,0],[0,-0.168],[-0.168,0],[0,0.168]],"v":[[-168.609,-106.922],[-168.305,-106.618],[-168,-106.922],[-168.305,-107.227]],"c":true}]}],"ix":2},"nm":"Path 1","mn":"ADBE Vector Shape - Group","hd":false},{"ty":"st","c":{"a":0,"k":[0.20000000298,0.800000011921,0.800000011921,1],"ix":3,"x":"var $bm_rt;\n$bm_rt = thisComp.layer('Main Stroke width - Color Ctrl').effect('Highlight')('Color');"},"o":{"a":0,"k":100,"ix":4},"w":{"a":0,"k":16,"ix":5,"x":"var $bm_rt;\n$bm_rt = thisComp.layer('Main Stroke width - Color Ctrl').effect('Stroke width')('Slider');"},"lc":2,"lj":2,"bm":0,"nm":"Stroke 1","mn":"ADBE Vector Graphic - Stroke","hd":false},{"ty":"tr","p":{"a":0,"k":[0,0],"ix":2},"a":{"a":0,"k":[0,0],"ix":1},"s":{"a":0,"k":[100,100],"ix":3},"r":{"a":0,"k":0,"ix":6},"o":{"a":0,"k":100,"ix":7},"sk":{"a":0,"k":0,"ix":4},"sa":{"a":0,"k":0,"ix":5},"nm":"Transform"}],"nm":"Group 1","np":3,"cix":2,"bm":0,"ix":1,"mn":"ADBE Vector Group","hd":false}],"ip":3,"op":64,"st":3,"ct":1,"bm":0},{"ddd":0,"ind":4,"ty":0,"nm":"Coin","parent":5,"refId":"comp_0","sr":1,"ks":{"o":{"a":0,"k":100,"ix":11},"r":{"a":0,"k":0,"ix":10},"p":{"a":1,"k":[{"i":{"x":0.833,"y":0.833},"o":{"x":0.167,"y":0.167},"t":0,"s":[0,33,0],"to":[0,-9.667,0],"ti":[0,0,0]},{"i":{"x":0.833,"y":0.833},"o":{"x":0.167,"y":0.167},"t":39,"s":[0,-25,0],"to":[0,0,0],"ti":[0,-9.667,0]},{"t":72,"s":[0,33,0]}],"ix":2,"l":2},"a":{"a":0,"k":[250,283,0],"ix":1,"l":2},"s":{"a":1,"k":[{"t":19,"s":[100,100,100],"h":1},{"t":20,"s":[100,-100,100],"h":1},{"t":56,"s":[100,-100,100],"h":1},{"t":57,"s":[100,100,100],"h":1}],"ix":6,"l":2}},"ao":0,"w":500,"h":500,"ip":0,"op":120,"st":0,"bm":0},{"ddd":0,"ind":5,"ty":3,"nm":"Zero | troke width - Color Ctrl","sr":1,"ks":{"o":{"a":0,"k":0,"ix":11},"r":{"a":0,"k":0,"ix":10},"p":{"a":0,"k":[250,250,0],"ix":2,"l":2},"a":{"a":0,"k":[0,0,0],"ix":1,"l":2},"s":{"a":0,"k":[100,100,100],"ix":6,"l":2}},"ao":0,"ip":0,"op":75,"st":0,"bm":0}],"markers":[]}